pdfxtmd.cpython-311-x86_64-linux-gnu.so
pdfxtmd-1.0.1.dist-info/METADATA
pdfxtmd-1.0.1.dist-info/WHEEL
pdfxtmd-1.0.1.dist-info/top_level.txt
pdfxtmd-1.0.1.dist-info/RECORD
pdfxtmd-1.0.1.dist-info/licenses/LICENSE
