Metadata-Version: 2.4
Name: pdfxtmd
Version: 1.0.1
Summary: PDFxTMD is a library for parton distribution functions (PDFs) that integrates both collinear PDFs (cPDFs) and transverse momentum-dependent PDFs (TMDs).
Home-page: https://github.com/Raminkord92/PDFxTMD
Author: Ramin Kord Valeshabadi
Author-email: Ramin Kord Valeshabadi <raminkord92@gmail.com>
License: GPL-3.0
Project-URL: Homepage, https://github.com/Raminkord92/PDFxTMD
Platform: any
Classifier: Programming Language :: Python :: 3
Classifier: License :: OSI Approved :: GNU General Public License v3 (GPLv3)
Classifier: Operating System :: OS Independent
Requires-Python: >=3.6
License-File: LICENSE
Dynamic: author
Dynamic: home-page
Dynamic: license-file
Dynamic: platform
Dynamic: requires-python
